Metadata-Version: 2.1
Name: x11_screen_capture
Version: 0.1.2
Summary: A Python module for screen capture and image encoding.
Home-page: 
Author: Ryan Kuba
Author-email: ryankuba@gmail.com
Classifier: Programming Language :: Python :: 3
Classifier: License :: OSI Approved :: GNU General Public License v3 or later (GPLv3+)
Classifier: Operating System :: POSIX :: Linux
Requires-Python: >=3.6
License-File: LICENSE
